krri_common/__init__.py
krri_common/adapters/__init__.py
krri_common/adapters/message_channel.py
krri_common/adapters/message_publisher.py
krri_common/adapters/message_receiver.py
krri_common/domain/__init__.py
krri_common/domain/phase_service.py
krri_common/models/__init__.py
krri_common/models/occupation_description.py
krri_common/models/prepared_phase_message.py
krri_common/models/spectrogram.py
krri_common/models/train_direction.py
krri_common/models/train_summary.py
krri_common/utils/__init__.py
krri_common/utils/das_math.py
krri_common/utils/fastnumpyio.py
krri_common/utils/krri_math.py
krri_common/utils/redis_numpy_helper.py
krri_common-0.7.0.dist-info/LICENSE
krri_common-0.7.0.dist-info/METADATA
krri_common-0.7.0.dist-info/WHEEL
krri_common-0.7.0.dist-info/top_level.txt
krri_common-0.7.0.dist-info/RECORD
