Metadata-Version: 2.1
Name: krri-common
Version: 0.7.0
Summary: KRRI rail broken detection common module
Home-page: https://github.com/krri_common
Author: hy1as
Author-email: mk-lee@aptechinc.com
License: BSD 2-clause
Classifier: Development Status :: 1 - Planning
Classifier: Intended Audience :: Science/Research
Classifier: License :: OSI Approved :: BSD License
Classifier: Operating System :: POSIX :: Linux
Classifier: Programming Language :: Python :: 3.11
License-File: LICENSE
Requires-Dist: aiormq ==6.7.7
Requires-Dist: matplotlib ~=3.8.3
Requires-Dist: msgspec ==0.18.4
Requires-Dist: numpy ~=1.26.4
Requires-Dist: pika ==1.3.2
Requires-Dist: pytest ~=7.4.1
Requires-Dist: redis ==5.0.1
Requires-Dist: setuptools ~=68.2.2
Requires-Dist: h5py ==3.9.0
Requires-Dist: Pillow ~=10.0.0
Requires-Dist: scipy ~=1.14.0
Requires-Dist: tiledb ==0.31.1
